qef
tests
