Metadata-Version: 1.1
Name: qef
Version: 0.2.2
Summary: quasielastic fitting
Home-page: https://github.com/jmborr/qef
Author: Jose Borreguero
Author-email: borreguero@gmail.com
License: MIT license
Keywords: qef
Platform: UNKNOWN
Classifier: Development Status :: 2 - Pre-Alpha
Classifier: Intended Audience :: Developers
Classifier: License :: OSI Approved :: MIT License
Classifier: Natural Language :: English
Classifier: Programming Language :: Python :: 2
Classifier: Programming Language :: Python :: 2.6
Classifier: Programming Language :: Python :: 2.7
Classifier: Programming Language :: Python :: 3
Classifier: Programming Language :: Python :: 3.3
Classifier: Programming Language :: Python :: 3.4
Classifier: Programming Language :: Python :: 3.5
